<root>
	<styles>
		<include src="file://{resources}/styles/dotastyles.css" />
		<include src="file://{resources}/styles/custom_game/buff_list.css" />
	</styles>
	<script>
		function OnBuffClicked()
		{
			var queryUnit = $.GetContextPanel().m_QueryUnit;
			var buffSerial = $.GetContextPanel().m_BuffSerial;
			var alertBuff = GameUI.IsAltDown();
			Players.BuffClicked( queryUnit, buffSerial, alertBuff );
		}

		function BuffShowTooltip()
		{
			$.Msg( "Hover Buff" );
			var queryUnit = $.GetContextPanel().m_QueryUnit;
			var buffSerial = $.GetContextPanel().m_BuffSerial;
			var isEnemy = Entities.IsEnemy( queryUnit );
			$.DispatchEvent( "DOTAShowBuffTooltip", $.GetContextPanel(), queryUnit, buffSerial, isEnemy );
		}

		function BuffHideTooltip()
		{
			$.DispatchEvent( "DOTAHideBuffTooltip", $.GetContextPanel() );
		}
	</script>
	<Panel class="BuffRoot" hittest="false">
		<Button id="BuffFrame"
							onactivate="OnBuffClicked()"
							onmouseover="BuffShowTooltip()"
							onmouseout="BuffHideTooltip()"
							>
			<Panel id="BuffImage">
				<DOTAAbilityImage id="AbilityImage" />
				<DOTAItemImage id="ItemImage" scaling="stretch-to-fit-y-preserve-aspect" />
			</Panel>
			<Panel id="BuffFrameUnder">
			</Panel>
			<Label id="StackCount" />
		</Button>
	</Panel>
</root>

